useful_wsi/__init__.py
useful_wsi/patch_sampling.py
useful_wsi/tissue_segmentation.py
useful_wsi/utils.py
useful_wsi/version.py
useful_wsi/visu_utils.py
useful_wsi-1.1.0.dist-info/LICENCE.txt
useful_wsi-1.1.0.dist-info/METADATA
useful_wsi-1.1.0.dist-info/WHEEL
useful_wsi-1.1.0.dist-info/top_level.txt
useful_wsi-1.1.0.dist-info/RECORD
