Metadata-Version: 2.1
Name: useful-wsi
Version: 1.1.0
Summary: UNKNOWN
Home-page: UNKNOWN
Author: Peter
Author-email: UNKNOWN
License: see LICENSE.txt
Platform: UNKNOWN
